adv_prodcon/__init__.py
adv_prodcon/adv_prodcon.py
adv_prodcon-0.1.14.dist-info/AUTHORS.rst
adv_prodcon-0.1.14.dist-info/LICENSE
adv_prodcon-0.1.14.dist-info/METADATA
adv_prodcon-0.1.14.dist-info/WHEEL
adv_prodcon-0.1.14.dist-info/top_level.txt
adv_prodcon-0.1.14.dist-info/RECORD
