Metadata-Version: 2.1
Name: adv-prodcon
Version: 0.1.14
Summary: Python package implementing a full featured producer/consumer pattern for concurrent workers
Home-page: https://github.com/acreegan/adv_prodcon
Author: Andrew Creegan
Author-email: andrew.s.creegan@gmail.com
License: MIT license
Keywords: adv_prodcon
Platform: UNKNOWN
Classifier: Development Status :: 2 - Pre-Alpha
Classifier: Intended Audience :: Developers
Classifier: License :: OSI Approved :: MIT License
Classifier: Natural Language :: English
Classifier: Programming Language :: Python :: 3
Classifier: Programming Language :: Python :: 3.6
Classifier: Programming Language :: Python :: 3.7
Classifier: Programming Language :: Python :: 3.8
Requires-Python: >=3.6
